purl/__init__.py
purl/template.py
purl/url.py
purl-1.6.dist-info/AUTHORS
purl-1.6.dist-info/LICENSE
purl-1.6.dist-info/METADATA
purl-1.6.dist-info/WHEEL
purl-1.6.dist-info/top_level.txt
purl-1.6.dist-info/RECORD
